fastpolvo/__init__.py
fastpolvo/_modidx.py
fastpolvo/core.py
fastpolvo/classification/__init__.py
fastpolvo/classification/explorer.py
fastpolvo/classification/baseline/__init__.py
fastpolvo/classification/baseline/baseline.py
fastpolvo/data/__init__.py
fastpolvo/data/transforms.py
fastpolvo/segmentation/__init__.py
fastpolvo/segmentation/core.py
fastpolvo-0.0.3.dist-info/LICENSE
fastpolvo-0.0.3.dist-info/METADATA
fastpolvo-0.0.3.dist-info/WHEEL
fastpolvo-0.0.3.dist-info/entry_points.txt
fastpolvo-0.0.3.dist-info/top_level.txt
fastpolvo-0.0.3.dist-info/RECORD
