Metadata-Version: 2.1
Name: fastpolvo
Version: 0.0.3
Summary: polvo tentacle for fastai
Home-page: https://github.com/lgvaz/fastpolvo
Author: lgvaz
Author-email: lgvaz42@gmail.com
License: Apache Software License 2.0
Keywords: nbdev jupyter notebook python
Classifier: Development Status :: 4 - Beta
Classifier: Intended Audience :: Developers
Classifier: Natural Language :: English
Classifier: Programming Language :: Python :: 3.7
Classifier: Programming Language :: Python :: 3.8
Classifier: Programming Language :: Python :: 3.9
Classifier: Programming Language :: Python :: 3.10
Classifier: License :: OSI Approved :: Apache Software License
Requires-Python: >=3.7
License-File: LICENSE
Provides-Extra: dev
